samu_ml_lab/__init__.py
samu_ml_lab/exercise1.py
samu_ml_lab-0.1.dist-info/METADATA
samu_ml_lab-0.1.dist-info/WHEEL
samu_ml_lab-0.1.dist-info/top_level.txt
samu_ml_lab-0.1.dist-info/RECORD
