Metadata-Version: 2.1
Name: samu_ml_lab
Version: 0.1
Summary: ML Lab Exercises Package
Author: pradhanya
Requires-Python: >=3.6
Requires-Dist: scikit-learn
